gubert/GcloudManager.py
gubert/KubectlManager.py
gubert/__init__.py
gubert/__main__.py
gubert/utils.py
gubert/views/DiscoverGcloudKubernetesCluster.py
gubert/views/DummyExitView.py
gubert/views/SwitchGcloudConfigration.py
gubert/views/View.py
gubert/views/__init__.py
gubert-0.0.3.dist-info/LICENSE
gubert-0.0.3.dist-info/METADATA
gubert-0.0.3.dist-info/WHEEL
gubert-0.0.3.dist-info/entry_points.txt
gubert-0.0.3.dist-info/top_level.txt
gubert-0.0.3.dist-info/RECORD
